odoo/addons/sale_order_sign_oca/README.rst
odoo/addons/sale_order_sign_oca/__init__.py
odoo/addons/sale_order_sign_oca/__manifest__.py
odoo/addons/sale_order_sign_oca/demo/sign_oca_role.xml
odoo/addons/sale_order_sign_oca/demo/sign_oca_template.xml
odoo/addons/sale_order_sign_oca/i18n/it.po
odoo/addons/sale_order_sign_oca/i18n/sale_order_sign_oca.pot
odoo/addons/sale_order_sign_oca/models/__init__.py
odoo/addons/sale_order_sign_oca/models/res_company.py
odoo/addons/sale_order_sign_oca/models/res_config_settings.py
odoo/addons/sale_order_sign_oca/models/sale_order.py
odoo/addons/sale_order_sign_oca/models/sign_oca_request.py
odoo/addons/sale_order_sign_oca/readme/CONFIGURE.md
odoo/addons/sale_order_sign_oca/readme/CONTRIBUTORS.md
odoo/addons/sale_order_sign_oca/readme/DESCRIPTION.md
odoo/addons/sale_order_sign_oca/readme/USAGE.md
odoo/addons/sale_order_sign_oca/security/sale_order_sign_oca_security.xml
odoo/addons/sale_order_sign_oca/static/description/icon.png
odoo/addons/sale_order_sign_oca/static/description/index.html
odoo/addons/sale_order_sign_oca/tests/__init__.py
odoo/addons/sale_order_sign_oca/tests/test_sale_order_sign_oca.py
odoo/addons/sale_order_sign_oca/views/res_config_settings.xml
odoo/addons/sale_order_sign_oca/views/sale_order.xml
odoo/addons/sale_order_sign_oca/views/sign_oca_request.xml
odoo14_addon_sale_order_sign_oca-14.0.1.0.1.dev3.dist-info/METADATA
odoo14_addon_sale_order_sign_oca-14.0.1.0.1.dev3.dist-info/WHEEL
odoo14_addon_sale_order_sign_oca-14.0.1.0.1.dev3.dist-info/top_level.txt
odoo14_addon_sale_order_sign_oca-14.0.1.0.1.dev3.dist-info/RECORD
